pelp/__init__.py
pelp/cli.py
pelp/jsutils.py
pelp/utils.py
Pelp-1.0.0.dist-info/LICENSE
Pelp-1.0.0.dist-info/METADATA
Pelp-1.0.0.dist-info/WHEEL
Pelp-1.0.0.dist-info/entry_points.txt
Pelp-1.0.0.dist-info/top_level.txt
Pelp-1.0.0.dist-info/RECORD
