Metadata-Version: 2.1
Name: Pelp
Version: 1.0.0
Summary: A cli for Programming Language Documentation
Home-page: https://github.com/gosulap/Pelp
Author: Pradhit Gosula
Author-email: pradhitg@gmail.com
License: UNKNOWN
Platform: UNKNOWN
Classifier: Programming Language :: Python :: 3
Classifier: License :: OSI Approved :: MIT License
Classifier: Operating System :: OS Independent
